LICENSE
MANIFEST.in
README.md
setup.py
kenger/__init__.py
kenger/__version__.py
kenger.egg-info/PKG-INFO
kenger.egg-info/SOURCES.txt
kenger.egg-info/dependency_links.txt
kenger.egg-info/requires.txt
kenger.egg-info/top_level.txt
kenger/PathPro/__init__.py
kenger/PathPro/path.py
kenger/变量存储与加载/__init__.py
kenger/变量存储与加载/varLD.py
kenger/变量存储与加载/varLDnp.py
kenger/打印的工具/__init__.py
kenger/执行命令行/__init__.py
kenger/时间戳变换以及时间段/__init__.py
kenger/邮件发送/__init__.py
kenger/邮件发送/message.py