Metadata-Version: 2.1
Name: kenger
Version: 0.0.2
Summary: kenger 0.0.2
Home-page: https://github.com/kengerlwl/myPackage
Author: kenger
Author-email: 2892211452@qq.com
License: MIT
Classifier: License :: OSI Approved :: MIT License
Classifier: Programming Language :: Python
Classifier: Programming Language :: Python :: 3
Classifier: Programming Language :: Python :: 3.8
Classifier: Programming Language :: Python :: Implementation :: CPython
Classifier: Programming Language :: Python :: Implementation :: PyPy
Requires-Python: >=3.6.0
License-File: LICENSE
